plone.app.contenttypes-4.0.8-py3.13-nspkg.pth
plone/app/contenttypes/__init__.py
plone/app/contenttypes/configure.zcml
plone/app/contenttypes/content.py
plone/app/contenttypes/indexers.py
plone/app/contenttypes/indexers.zcml
plone/app/contenttypes/interfaces.py
plone/app/contenttypes/permissions.py
plone/app/contenttypes/permissions.zcml
plone/app/contenttypes/profiles.zcml
plone/app/contenttypes/setuphandlers.py
plone/app/contenttypes/subscribers.py
plone/app/contenttypes/subscribers.zcml
plone/app/contenttypes/testing.py
plone/app/contenttypes/upgrades.py
plone/app/contenttypes/upgrades.zcml
plone/app/contenttypes/utils.py
plone/app/contenttypes/behaviors/__init__.py
plone/app/contenttypes/behaviors/collection.py
plone/app/contenttypes/behaviors/configure.zcml
plone/app/contenttypes/behaviors/leadimage.pt
plone/app/contenttypes/behaviors/leadimage.py
plone/app/contenttypes/behaviors/richtext.py
plone/app/contenttypes/behaviors/richtext_gettext.pt
plone/app/contenttypes/behaviors/tableofcontents.py
plone/app/contenttypes/behaviors/thumb_icon.py
plone/app/contenttypes/behaviors/viewlets.py
plone/app/contenttypes/browser/__init__.py
plone/app/contenttypes/browser/collection.py
plone/app/contenttypes/browser/configure.zcml
plone/app/contenttypes/browser/file.py
plone/app/contenttypes/browser/folder.py
plone/app/contenttypes/browser/full_view.py
plone/app/contenttypes/browser/link_redirect_view.py
plone/app/contenttypes/browser/migration.py
plone/app/contenttypes/browser/utils.py
plone/app/contenttypes/browser/images/icon_export_ical.png
plone/app/contenttypes/browser/images/icon_export_vcal.png
plone/app/contenttypes/browser/templates/document.pt
plone/app/contenttypes/browser/templates/file.pt
plone/app/contenttypes/browser/templates/full_view.pt
plone/app/contenttypes/browser/templates/full_view_item.pt
plone/app/contenttypes/browser/templates/image.pt
plone/app/contenttypes/browser/templates/image_view_fullscreen.pt
plone/app/contenttypes/browser/templates/link.pt
plone_app_contenttypes-4.0.8.dist-info/METADATA
plone_app_contenttypes-4.0.8.dist-info/WHEEL
plone_app_contenttypes-4.0.8.dist-info/namespace_packages.txt
plone_app_contenttypes-4.0.8.dist-info/top_level.txt
plone_app_contenttypes-4.0.8.dist-info/RECORD
