Metadata-Version: 2.4
Name: plone.app.contenttypes
Version: 4.0.8
Summary: Default content types for Plone based on Dexterity
Home-page: https://github.com/plone/plone.app.contenttypes
Author: Plone Foundation
Author-email: plone-developers@lists.sourceforge.net
License: GPL
Keywords: plone content types dexterity
Classifier: Development Status :: 5 - Production/Stable
Classifier: Environment :: Web Environment
Classifier: Framework :: Plone
Classifier: Framework :: Plone :: 6.1
Classifier: Framework :: Plone :: Core
Classifier: Framework :: Zope :: 5
Classifier: License :: OSI Approved :: GNU General Public License v2 (GPLv2)
Classifier: Operating System :: OS Independent
Classifier: Programming Language :: Python
Classifier: Programming Language :: Python :: 3.10
Classifier: Programming Language :: Python :: 3.11
Classifier: Programming Language :: Python :: 3.12
Requires-Python: >=3.10
Requires-Dist: setuptools
Requires-Dist: plone.app.contentmenu
Requires-Dist: plone.app.dexterity>=2.0.7
Requires-Dist: plone.app.linkintegrity
Requires-Dist: plone.app.querystring>=1.2.2
Requires-Dist: plone.dexterity>=2.2.1
Requires-Dist: plone.app.relationfield
Requires-Dist: plone.namedfile>=4.2.0
Requires-Dist: plone.app.versioningbehavior
Requires-Dist: plone.app.vocabularies>4.1.2
Requires-Dist: plone.app.lockingbehavior
Requires-Dist: plone.behavior>=1.3.0
Requires-Dist: plone.app.z3cform>=1.1.0
Requires-Dist: plone.base
Requires-Dist: Products.BTreeFolder2
Requires-Dist: Products.GenericSetup
Requires-Dist: Products.MimetypesRegistry
Requires-Dist: Products.PortalTransforms
Requires-Dist: Products.statusmessages
Requires-Dist: plone.app.layout
Requires-Dist: plone.app.textfield
Requires-Dist: plone.app.uuid
Requires-Dist: plone.autoform
Requires-Dist: plone.event
Requires-Dist: plone.folder
Requires-Dist: plone.indexer
Requires-Dist: plone.memoize
Requires-Dist: plone.portlets
Requires-Dist: plone.registry
Requires-Dist: plone.rfc822
Requires-Dist: plone.supermodel
Requires-Dist: plone.z3cform
Requires-Dist: z3c.form
Requires-Dist: Zope
Provides-Extra: test
Requires-Dist: lxml; extra == "test"
Requires-Dist: plone.app.robotframework[debug]>0.9.8; extra == "test"
Requires-Dist: plone.app.testing[robot]>=4.2.4; extra == "test"
Requires-Dist: plone.testing; extra == "test"
Requires-Dist: plone.browserlayer; extra == "test"
Requires-Dist: plone.uuid; extra == "test"
Requires-Dist: robotsuite; extra == "test"
Dynamic: author
Dynamic: author-email
Dynamic: classifier
Dynamic: description
Dynamic: home-page
Dynamic: keywords
Dynamic: license
Dynamic: provides-extra
Dynamic: requires-dist
Dynamic: requires-python
Dynamic: summary
